checkerpointrescue/__init__.py
checkerpointrescue/checkpoint.py
checkerpointrescue-0.0.2.dist-info/LICENSE
checkerpointrescue-0.0.2.dist-info/METADATA
checkerpointrescue-0.0.2.dist-info/WHEEL
checkerpointrescue-0.0.2.dist-info/top_level.txt
checkerpointrescue-0.0.2.dist-info/RECORD
